{
  "id": "devotional-2025-10-05",
  "date": "2025-10-05",
  "title": "Whispers in the Cosmic Cathedral",
  "content": "The night sky transforms into a vast cathedral tonight. With full moon serving as heaven's lantern at 100% brightness, Jupiter, Saturn, Venus (Evening Star) become altar candles in the cosmic sanctuary. The Great Square of Pegasus marks the season serves as tonight's celestial sermon, preached without words yet heard by every searching heart. In this autumn season over Macon, Georgia, creation's testimony grows louder in the quiet hours. Ancient light from distant stars reaches your eyes tonight—photons that began their journey years ago, arriving at precisely this moment to remind you of timeless truth. God speaks through the grandeur above, inviting you into deeper communion. During after 10:00 pm (moon provides natural light), find a quiet spot and simply be present. Let the majesty overhead draw your spirit toward the Divine presence that fills every inch of space yet dwells intimately within your heart.",
  "scriptureReference": "Job 9:9",
  "celestialConnection": "Pegasus and Andromeda grace tonight's sky. Jupiter, Saturn, Venus (Evening Star) shine as faithful witnesses to God's creative power across autumn evenings.",
  "theme": "wonder",
  "moonPhase": "Full Moon",
  "moonIllumination": "100%",
  "visiblePlanets": "Jupiter, Saturn, Venus (Evening Star)",
  "specialEvents": "The Great Square of Pegasus marks the season",
  "constellations": [
    "Pegasus",
    "Andromeda",
    "Cassiopeia",
    "Perseus",
    "Aquarius"
  ],
  "bestViewingTime": "After 10:00 PM (moon provides natural light)",
  "season": "Autumn",
  "location": "Macon, Georgia",
  "createdAt": "2025-10-05T01:06:00.878Z",
  "isFallback": false,
  "version": "2.0"
}