{
  "app": "Our Night Sky",
  "date": "2026-04-17",
  "provider": "multi-fallback",
  "words": 239,
  "hemisphere": "Northern",
  "content_markdown": "# Galactic Convergence: A Celestial Witness to Unity\n## Scripture\n\"But God has combined the members of the body and has given greater honor to the parts that lacked it, so that there should be no division in the body, but that its parts should have equal concern for each other.\" - 1 Corinthians 12:24-25\n\n## Reflection\nAs we gaze upon the night sky, we're reminded of the majestic dance of celestial bodies. The convergence of galaxies, like the Whirlpool Galaxy and its companions, demonstrates the intricate harmony that exists in the universe. Just as these galaxies orbit and interact with one another, our lives are intertwined with those around us. The apostle Paul reminds us that, as members of the body of Christ, we're called to unity and mutual support. Just as the universe converges in a grand symphony, we too can come together in perfect harmony, valuing and honoring each other's unique contributions.\n\n## Prayer\nDear Heavenly Father, as we marvel at the convergence of galaxies in the night sky, remind us of the beauty of unity and harmony in the body of Christ. Help us to recognize the value and worth of every individual, and to work together in perfect sync, just as the celestial bodies dance across the universe. May our lives be a reflection of Your grand design, and may we bring glory to You as we move in harmony with one another. Amen.",
  "generated_at": "2026-04-17T09:28:01.830Z",
  "uniqueness_check": "passed"
}