{
  "app": "Our Night Sky",
  "date": "2026-04-22",
  "provider": "multi-fallback",
  "words": 212,
  "hemisphere": "Northern",
  "content_markdown": "# Lunar Cycles and Faithful Renewal\n## Scripture\n\"But those who hope in the Lord will renew their strength. They will soar on wings like eagles; they will run and not grow weary, they will walk and not be faint.\" - Isaiah 40:31\n\n## Reflection\nAs we gaze up at the night sky, we're reminded of the lunar cycles that govern the tides and the seasons. The moon waxes and wanes, a constant reminder of the ebbs and flows of life. Yet, even in the darkest phases, the moon remains, a steady presence in the darkness. So too, our faith is strengthened by the promise of God's faithful renewal. Just as the moon is reborn with each new cycle, our spirits can be renewed by the hope we have in the Lord.\n\n## Prayer\nDear Heavenly Father, as we observe the lunar cycles, remind us of your faithful promise to renew our strength. Help us to soar on wings like eagles, to run without growing weary, and to walk without fainting. May our hope in you be the guiding force in our lives, illuminating even the darkest phases. Renew our spirits, O Lord, and grant us the courage to face each new day with confidence in your eternal love and care. Amen.",
  "generated_at": "2026-04-22T09:28:31.602Z",
  "uniqueness_check": "passed"
}